LICENSE.txt
README.rst
setup.py
genignore/__init__.py
genignore/cli.py
genignore/core.py
genignore/helpers.py
genignore/main.py
genignore/updaters.py
genignore.egg-info/PKG-INFO
genignore.egg-info/SOURCES.txt
genignore.egg-info/dependency_links.txt
genignore.egg-info/entry_points.txt
genignore.egg-info/requires.txt
genignore.egg-info/top_level.txt
genignore/tests/__init__.py
genignore/tests/functional_test.py
genignore/tests/test_genignore.py
genignore/tests/test_helpers.py