Metadata-Version: 2.1
Name: genignore
Version: 0.5.7
Summary: Generate gitignore files based on templates provided by github
Home-page: https://pypi.python.org/pypi/genignore
Author: Panos Kountanis
Author-email: panosktn@gmail.com
License: UNKNOWN
Platform: UNKNOWN
License-File: LICENSE.txt
